[
	{
		"name":"LuckyBao",
		"sub":[
			{
				"name":"src",
				"sub":[
					{
						"name":"commpany",
						"sub":[
							{
								"name":"footer",
								"sub":[
									"index1.vue",
									"index2.vue"
								]
							},
							{
								"name":"footer2",
								"sub":[
									"index1.vue",
									"index2.vue"
								]
							},
							{
								"name":"footer3",
								"sub":[
									"index1.vue",
									"index2.vue"
								]
							}
						]
					},
					{
						"name":"commpany2",
						"sub":[
							{
								"name":"footer",
								"sub":[
									"index1.vue",
									"index2.vue"
								]
							},
							{
								"name":"footer2",
								"sub":[
									"index1.vue",
									"index2.vue"
								]
							},
							{
								"name":"footer3",
								"sub":[
									"index1.vue",
									"index2.vue"
								]
							}
						]
					},
					{
						"name":"commpany3",
						"sub":[
							{
								"name":"footer",
								"sub":[
									"index1.vue",
									"index2.vue"
								]
							},
							{
								"name":"footer2",
								"sub":[
									"index1.vue",
									"index2.vue"
								]
							},
							{
								"name":"footer3",
								"sub":[
									"index1.vue",
									"index2.vue"
								]
							}
						]
					}
				]
			},
			{
				"name":"config",
				"sub":[
					"config.txt",
					"config.txt"	
					
				]
			}
		]
	},
	{
		"name":"level1",
		"sub":[
			"文件1.vue"
		]
	}


]